apps/__init__.py
apps/client_config.py
apps/desk_routing.py
apps/desks.py
apps/feature_preview.py
apps/links.py
apps/monitoring.py
apps/picture_renditions.py
apps/preferences.py
apps/privilege.py
apps/spikes.py
apps/stages.py
apps/tasks.py
apps/usage_metrics.py
apps/archive/__init__.py
apps/archive/archive.py
apps/archive/archive_correction.py
apps/archive/archive_link.py
apps/archive/archive_lock.py
apps/archive/archive_media.py
apps/archive/archive_rewrite.py
apps/archive/archive_spike.py
apps/archive/autocomplete.py
apps/archive/commands.py
apps/archive/common.py
apps/archive/ingest.py
apps/archive/item_comments.py
apps/archive/news.py
apps/archive/related.py
apps/archive/usage.py
apps/archive/usage_tracking.py
apps/archive/user_content.py
apps/archive_broadcast/__init__.py
apps/archive_broadcast/broadcast.py
apps/archive_history/__init__.py
apps/archive_history/service.py
apps/archived/__init__.py
apps/archived/archived.py
apps/auth/__init__.py
apps/auth/auth.py
apps/auth/errors.py
apps/auth/service.py
apps/auth/session_purge.py
apps/auth/sessions.py
apps/auth/db/__init__.py
apps/auth/db/change_password.py
apps/auth/db/commands.py
apps/auth/db/db.py
apps/auth/db/reset_password.py
apps/auth/oidc/__init__.py
apps/auth/oidc/auth.py
apps/auth/xmpp/__init__.py
apps/auth/xmpp/auth.py
apps/comments/__init__.py
apps/comments/comments.py
apps/comments/inline_comments.py
apps/comments/user_mentions.py
apps/common/__init__.py
apps/common/components/__init__.py
apps/common/components/base_component.py
apps/common/components/utils.py
apps/common/models/__init__.py
apps/common/models/base_model.py
apps/common/models/utils.py
apps/common/models/io/__init__.py
apps/common/models/io/base_proxy.py
apps/common/models/io/base_proxy_tests.py
apps/common/models/io/data_layer.py
apps/common/models/io/eve_proxy.py
apps/common/models/io/mongo_proxy.py
apps/concept_items/__init__.py
apps/concept_items/enums.py
apps/concept_items/resource.py
apps/concept_items/service.py
Superdesk_Core-2.5.3.dist-info/AUTHORS.md
Superdesk_Core-2.5.3.dist-info/LICENSE
Superdesk_Core-2.5.3.dist-info/METADATA
Superdesk_Core-2.5.3.dist-info/WHEEL
Superdesk_Core-2.5.3.dist-info/top_level.txt
Superdesk_Core-2.5.3.dist-info/RECORD
