Metadata-Version: 2.1
Name: Superdesk-Core
Version: 2.5.3
Summary: Superdesk Core library
Home-page: https://github.com/superdesk/superdesk-core
Author: petr jasek
Author-email: petr.jasek@sourcefabric.org
License: GPLv3
Platform: any
Classifier: Development Status :: 4 - Beta
Classifier: Environment :: Web Environment
Classifier: Intended Audience :: Developers
Classifier: License :: OSI Approved :: GNU General Public License v3 (GPLv3)
Classifier: Operating System :: OS Independent
Classifier: Programming Language :: Python
Classifier: Programming Language :: Python :: 3
Classifier: Topic :: Internet :: WWW/HTTP :: Dynamic Content
License-File: LICENSE
License-File: AUTHORS.md
Requires-Dist: urllib3 (<1.26)
Requires-Dist: eve (==1.1.2)
Requires-Dist: eve-elastic (<7.2.0,>=7.1.3)
Requires-Dist: flask (<1.2,>=1.1)
Requires-Dist: flask-mail (<0.10,>=0.9)
Requires-Dist: flask-script (<3.0,>=2.0.5)
Requires-Dist: flask-babel (<1.1,>=1.0)
Requires-Dist: pillow (<9.3,>=9.2)
Requires-Dist: arrow (<=0.13,>=0.4)
Requires-Dist: bcrypt (<3.2,>=3.1.1)
Requires-Dist: blinker (<1.5,>=1.3)
Requires-Dist: celery[redis] (<4.5,>=4.4.0)
Requires-Dist: cerberus (<1.4,>=1.3.2)
Requires-Dist: redis (<3.3,>=3.2.0)
Requires-Dist: kombu (<4.7,>=4.6)
Requires-Dist: feedparser (<6.1,>=6.0.8)
Requires-Dist: hachoir (<=3.0a3)
Requires-Dist: HermesCache (<0.11.0,>=0.10.0)
Requires-Dist: python-magic (<0.5,>=0.4)
Requires-Dist: ldap3 (<2.6,>=2.2.4)
Requires-Dist: pytz (>=2015.4)
Requires-Dist: tzlocal (<3.0,>=2.1)
Requires-Dist: raven[flask] (<7.0,>=5.10)
Requires-Dist: requests (<3.0,>=2.7.0)
Requires-Dist: boto3 (<2,>=1.18.42)
Requires-Dist: websockets (<7.0,>=3.0)
Requires-Dist: mongolock (<1.4,>=1.3.4)
Requires-Dist: PyYAML (<6.0,>=5.3.1)
Requires-Dist: lxml (<4.7,>=4)
Requires-Dist: python-twitter (==3.5)
Requires-Dist: chardet (<4.0)
Requires-Dist: pymongo (<3.12,>=3.8)
Requires-Dist: croniter (<0.4)
Requires-Dist: python-dateutil (<2.8)
Requires-Dist: unidecode (==0.04.21)
Requires-Dist: authlib (<0.15,>0.14)
Requires-Dist: draftjs-exporter[lxml] (<2.2)
Requires-Dist: werkzeug (<1.1,>=1.0)
Requires-Dist: regex (==2020.7.14)
Requires-Dist: flask-oidc-ex (==0.5.5)
Requires-Dist: importlib-metadata (<3.2)
Requires-Dist: typing-extensions (>=3.7.4)
Requires-Dist: elastic-apm[flask] (<6.8,>=6.7)
Requires-Dist: MarkupSafe (<2.1)
